{
  "collectionName": "components_sections_slides",
  "info": {
    "displayName": "slides"
  },
  "options": {},
  "attributes": {
    "image": {
      "type": "media",
      "multiple": false,
      "allowedTypes": [
        "images",
        "files",
        "videos",
        "audios"
      ]
    },
    "caption": {
      "type": "string"
    },
    "x": {
  "type": "integer",
  "default": 0
},
"y": {
  "type": "integer",
  "default": 0
},
"width": {
  "type": "integer",
  "default": 400
},
"height": {
  "type": "integer",
  "default": 200
}
  },
  "config": {}
}
